[
  {
    "inputs": [],
    "stateMutability": "nonpayable",
    "type": "constructor"
  },
  {
    "inputs": [],
    "name": "CallerIsNotAssetManager",
    "type": "error"
  },
  {
    "inputs": [],
    "name": "ContractIsNotPaused",
    "type": "error"
  },
  {
    "inputs": [],
    "name": "DivBy0Sumweight",
    "type": "error"
  },
  {
    "inputs": [],
    "name": "InvalidAddress",
    "type": "error"
  },
  {
    "inputs": [],
    "name": "InvalidAmount",
    "type": "error"
  },
  {
    "inputs": [],
    "name": "InvalidSlippageLength",
    "type": "error"
  },
  {
    "inputs": [
      {
        "internalType": "uint256",
        "name": "totalWeight",
        "type": "uint256"
      }
    ],
    "name": "InvalidWeights",
    "type": "error"
  },
  {
    "inputs": [],
    "name": "LengthsDontMatch",
    "type": "error"
  },
  {
    "inputs": [],
    "name": "OnlyAssetManagerCanCallUnpause",
    "type": "error"
  },
  {
    "inputs": [],
    "name": "ProtocolIsPaused",
    "type": "error"
  },
  {
    "inputs": [],
    "name": "SwapHandlerNotEnabled",
    "type": "error"
  },
  {
    "inputs": [],
    "name": "TenMinutesPassOrRebalancingHasToBeCalled",
    "type": "error"
  },
  {
    "inputs": [],
    "name": "TokenNotApproved",
    "type": "error"
  },
  {
    "inputs": [],
    "name": "TokenNotWhitelisted",
    "type": "error"
  },
  {
    "inputs": [],
    "name": "TokensNotStaked",
    "type": "error"
  },
  {
    "inputs": [],
    "name": "WeightNotGreaterThan0",
    "type": "error"
  },
  {
    "anonymous": false,
    "inputs": [
      {
        "indexed": false,
        "internalType": "address",
        "name": "previousAdmin",
        "type": "address"
      },
      {
        "indexed": false,
        "internalType": "address",
        "name": "newAdmin",
        "type": "address"
      }
    ],
    "name": "AdminChanged",
    "type": "event"
  },
  {
    "anonymous": false,
    "inputs": [
      {
        "indexed": true,
        "internalType": "address",
        "name": "beacon",
        "type": "address"
      }
    ],
    "name": "BeaconUpgraded",
    "type": "event"
  },
  {
    "anonymous": false,
    "inputs": [
      {
        "indexed": true,
        "internalType": "address",
        "name": "previousOwner",
        "type": "address"
      },
      {
        "indexed": true,
        "internalType": "address",
        "name": "newOwner",
        "type": "address"
      }
    ],
    "name": "OwnershipTransferred",
    "type": "event"
  },
  {
    "anonymous": false,
    "inputs": [
      {
        "indexed": false,
        "internalType": "uint256",
        "name": "updated",
        "type": "uint256"
      },
      {
        "indexed": false,
        "internalType": "address[]",
        "name": "newTokens",
        "type": "address[]"
      },
      {
        "indexed": false,
        "internalType": "uint96[]",
        "name": "newDenorms",
        "type": "uint96[]"
      }
    ],
    "name": "UpdatedTokens",
    "type": "event"
  },
  {
    "anonymous": false,
    "inputs": [
      {
        "indexed": false,
        "internalType": "uint256",
        "name": "updated",
        "type": "uint256"
      },
      {
        "indexed": false,
        "internalType": "uint96[]",
        "name": "newDenorms",
        "type": "uint96[]"
      }
    ],
    "name": "UpdatedWeights",
    "type": "event"
  },
  {
    "anonymous": false,
    "inputs": [
      {
        "indexed": true,
        "internalType": "address",
        "name": "implementation",
        "type": "address"
      }
    ],
    "name": "Upgraded",
    "type": "event"
  },
  {
    "inputs": [
      {
        "internalType": "address[]",
        "name": "_tokens",
        "type": "address[]"
      },
      {
        "internalType": "uint96[]",
        "name": "_denorms",
        "type": "uint96[]"
      }
    ],
    "name": "_updateTokenListAndRecords",
    "outputs": [],
    "stateMutability": "nonpayable",
    "type": "function"
  },
  {
    "inputs": [],
    "name": "accessController",
    "outputs": [
      {
        "internalType": "contract AccessController",
        "name": "",
        "type": "address"
      }
    ],
    "stateMutability": "view",
    "type": "function"
  },
  {
    "inputs": [],
    "name": "assetManagerConfig",
    "outputs": [
      {
        "internalType": "contract IAssetManagerConfig",
        "name": "",
        "type": "address"
      }
    ],
    "stateMutability": "view",
    "type": "function"
  },
  {
    "inputs": [],
    "name": "exchange",
    "outputs": [
      {
        "internalType": "contract IExchange",
        "name": "",
        "type": "address"
      }
    ],
    "stateMutability": "view",
    "type": "function"
  },
  {
    "inputs": [
      {
        "internalType": "address",
        "name": "_token",
        "type": "address"
      }
    ],
    "name": "getTokenBalance",
    "outputs": [
      {
        "internalType": "uint256",
        "name": "",
        "type": "uint256"
      }
    ],
    "stateMutability": "view",
    "type": "function"
  },
  {
    "inputs": [],
    "name": "index",
    "outputs": [
      {
        "internalType": "contract IIndexSwap",
        "name": "",
        "type": "address"
      }
    ],
    "stateMutability": "view",
    "type": "function"
  },
  {
    "inputs": [
      {
        "internalType": "address",
        "name": "_index",
        "type": "address"
      },
      {
        "internalType": "address",
        "name": "_accessController",
        "type": "address"
      }
    ],
    "name": "init",
    "outputs": [],
    "stateMutability": "nonpayable",
    "type": "function"
  },
  {
    "inputs": [],
    "name": "lastPaused",
    "outputs": [
      {
        "internalType": "uint256",
        "name": "",
        "type": "uint256"
      }
    ],
    "stateMutability": "view",
    "type": "function"
  },
  {
    "inputs": [],
    "name": "oracle",
    "outputs": [
      {
        "internalType": "contract IPriceOracle",
        "name": "",
        "type": "address"
      }
    ],
    "stateMutability": "view",
    "type": "function"
  },
  {
    "inputs": [],
    "name": "owner",
    "outputs": [
      {
        "internalType": "address",
        "name": "",
        "type": "address"
      }
    ],
    "stateMutability": "view",
    "type": "function"
  },
  {
    "inputs": [],
    "name": "renounceOwnership",
    "outputs": [],
    "stateMutability": "nonpayable",
    "type": "function"
  },
  {
    "inputs": [
      {
        "internalType": "bool",
        "name": "_state",
        "type": "bool"
      }
    ],
    "name": "setPause",
    "outputs": [],
    "stateMutability": "nonpayable",
    "type": "function"
  },
  {
    "inputs": [],
    "name": "tokenRegistry",
    "outputs": [
      {
        "internalType": "contract ITokenRegistry",
        "name": "",
        "type": "address"
      }
    ],
    "stateMutability": "view",
    "type": "function"
  },
  {
    "inputs": [
      {
        "internalType": "address",
        "name": "newOwner",
        "type": "address"
      }
    ],
    "name": "transferOwnership",
    "outputs": [],
    "stateMutability": "nonpayable",
    "type": "function"
  },
  {
    "inputs": [
      {
        "internalType": "address[]",
        "name": "tokens",
        "type": "address[]"
      },
      {
        "internalType": "uint96[]",
        "name": "denorms",
        "type": "uint96[]"
      },
      {
        "internalType": "uint256[]",
        "name": "_slippageSell",
        "type": "uint256[]"
      },
      {
        "internalType": "uint256[]",
        "name": "_slippageBuy",
        "type": "uint256[]"
      },
      {
        "internalType": "address",
        "name": "_swapHandler",
        "type": "address"
      }
    ],
    "name": "updateTokens",
    "outputs": [],
    "stateMutability": "nonpayable",
    "type": "function"
  },
  {
    "inputs": [
      {
        "internalType": "uint96[]",
        "name": "denorms",
        "type": "uint96[]"
      },
      {
        "internalType": "uint256[]",
        "name": "_slippage",
        "type": "uint256[]"
      },
      {
        "internalType": "address",
        "name": "_swapHandler",
        "type": "address"
      }
    ],
    "name": "updateWeights",
    "outputs": [],
    "stateMutability": "nonpayable",
    "type": "function"
  },
  {
    "inputs": [
      {
        "internalType": "address",
        "name": "newImplementation",
        "type": "address"
      }
    ],
    "name": "upgradeTo",
    "outputs": [],
    "stateMutability": "nonpayable",
    "type": "function"
  },
  {
    "inputs": [
      {
        "internalType": "address",
        "name": "newImplementation",
        "type": "address"
      },
      {
        "internalType": "bytes",
        "name": "data",
        "type": "bytes"
      }
    ],
    "name": "upgradeToAndCall",
    "outputs": [],
    "stateMutability": "payable",
    "type": "function"
  },
  {
    "stateMutability": "payable",
    "type": "receive"
  }
]
